[
    {
        "AssetId": "10100443", 
        "Name": "Universal Connector", 
        "AssetSetId": "2", 
        "IsTrusted": "True", 
        "AssetVersionId": "25509660", 
        "CreatorName": "Roblox"
    },
    {
        "AssetId": "10100422", 
        "Name": "Weld Connector", 
        "AssetSetId": "2", 
        "IsTrusted": "True", 
        "AssetVersionId": "25509626", 
        "CreatorName": "Roblox"
    },
    {
        "AssetId": "10100614", 
        "Name": "Wooden Wheel", 
        "AssetSetId": "2", 
        "IsTrusted": "True", 
        "AssetVersionId": "25510021", 
        "CreatorName": "Roblox"
    },
    {
        "AssetId": "10100552", 
        "Name": "Welded Plastic Ball", 
        "AssetSetId": "2", 
        "IsTrusted": "True", 
        "AssetVersionId": "25509903", 
        "CreatorName": "Roblox"
    },
    {
        "AssetId": "10100483", 
        "Name": "Smooth Wooden Ball", 
        "AssetSetId": "2", 
        "IsTrusted": "True", 
        "AssetVersionId": "25509940", 
        "CreatorName": "Roblox"
    },
    {
        "AssetId": "10099981", 
        "Name": "Shiny Aluminium Truss Beam", 
        "AssetSetId": "2", 
        "IsTrusted": "True", 
        "AssetVersionId": "25508706", 
        "CreatorName": "Roblox"
    },
    {
        "AssetId": "10099923", 
        "Name": "Wooden Truss Beam", 
        "AssetSetId": "2", 
        "IsTrusted": "True", 
        "AssetVersionId": "25508805", 
        "CreatorName": "Roblox"
    },
    {
        "AssetId": "10100297", 
        "Name": "Shiny Brick", 
        "AssetSetId": "2", 
        "IsTrusted": "True", 
        "AssetVersionId": "25509378", 
        "CreatorName": "Roblox"
    },
    {
        "AssetId": "10100083", 
        "Name": "Stone Brick", 
        "AssetSetId": "2", 
        "IsTrusted": "True", 
        "AssetVersionId": "25508931", 
        "CreatorName": "Roblox"
    },
    {
        "AssetId": "10479928", 
        "Name": "Car Seat", 
        "AssetSetId": "2", 
        "IsTrusted": "True", 
        "AssetVersionId": "26455265", 
        "CreatorName": "Roblox"
    },
    {
        "AssetId": "10479956", 
        "Name": "Big Car Seat", 
        "AssetSetId": "2", 
        "IsTrusted": "True", 
        "AssetVersionId": "26455346", 
        "CreatorName": "Roblox"
    },
    {
        "AssetId": "10480158", 
        "Name": "Small Spherical Wheel", 
        "AssetSetId": "2", 
        "IsTrusted": "True", 
        "AssetVersionId": "26455891", 
        "CreatorName": "Roblox"
    },
    {
        "AssetId": "10480095", 
        "Name": "Small Wooden Wheel", 
        "AssetSetId": "2", 
        "IsTrusted": "True", 
        "AssetVersionId": "26455724", 
        "CreatorName": "Roblox"
    },
    {
        "AssetId": "22886057", 
        "Name": "Wooden Wedge", 
        "AssetSetId": "2", 
        "IsTrusted": "True", 
        "AssetVersionId": "57057328", 
        "CreatorName": "Roblox"
    },
    {
        "AssetId": "22886061", 
        "Name": "Ice Wedge", 
        "AssetSetId": "2", 
        "IsTrusted": "True", 
        "AssetVersionId": "57057333", 
        "CreatorName": "Roblox"
    },
    {
        "AssetId": "37590189", 
        "Name": "4 x 4 x 4 Block", 
        "AssetSetId": "2", 
        "IsTrusted": "True", 
        "AssetVersionId": "92399223", 
        "CreatorName": "Roblox"
    },
    {
        "AssetId": "37740061", 
        "Name": "4 by 4 by 4 with welds", 
        "AssetSetId": "2", 
        "IsTrusted": "True", 
        "AssetVersionId": "92724321", 
        "CreatorName": "Roblox"
    }
]